{
    "keep": {
        "days": true,
        "amount": 14
    },
    "auditLog": "C:\\Users\\rafiu\\OneDrive\\Desktop\\My_Resources\\My_Files\\Learning_Dev_Resources\\Courses\\PH-2\\Projects\\university-management-core-service-starter\\logs\\winston\\errors\\.e178d4b152b9a10a66626530c722cb84a3f43bcf-audit.json",
    "files": [
        {
            "date": 1711994488191,
            "name": "C:\\Users\\rafiu\\OneDrive\\Desktop\\My_Resources\\My_Files\\Learning_Dev_Resources\\Courses\\PH-2\\Projects\\university-management-core-service-starter\\logs\\winston\\errors\\phu-2024-02-04-00-error.log",
            "hash": "0d4aa8a184149bd28b49391521197e16e717dc63b885552dff129c4ccbdff1aa"
        },
        {
            "date": 1712080159455,
            "name": "C:\\Users\\rafiu\\OneDrive\\Desktop\\My_Resources\\My_Files\\Learning_Dev_Resources\\Courses\\PH-2\\Projects\\university-management-core-service-starter\\logs\\winston\\errors\\phu-2024-02-04-23-error.log",
            "hash": "cdafe5f65ba0deca7ab84605c5537470a66e83187c2119bc0b75ed2c36f84219"
        },
        {
            "date": 1712100768838,
            "name": "C:\\Users\\rafiu\\OneDrive\\Desktop\\My_Resources\\My_Files\\Learning_Dev_Resources\\Courses\\PH-2\\Projects\\university-management-core-service-starter\\logs\\winston\\errors\\phu-2024-03-04-05-error.log",
            "hash": "7b9f883dd27c14872043241c17f2f206d6e5bdc1891c818cd105385b54cb6498"
        }
    ],
    "hashType": "sha256"
}